generate_usernames/__init__.py
generate_usernames/main.py
dynamic_username_generator_ai-3.1.dist-info/METADATA
dynamic_username_generator_ai-3.1.dist-info/WHEEL
dynamic_username_generator_ai-3.1.dist-info/top_level.txt
dynamic_username_generator_ai-3.1.dist-info/RECORD
