Metadata-Version: 2.1
Name: dynamic-username-generator-ai
Version: 3.1
Summary: Experience the power of OpenAI with our Dynamic Username Generator, a Python package offering personalized and creative usernames tailored to your unique preferences
Home-page: https://usernamegenerator.io/
Author: Bellamy
Author-email: usernamegenerator.io@gmail.com
License: UNKNOWN
Platform: UNKNOWN
Classifier: Programming Language :: Python :: 3
Classifier: License :: OSI Approved :: MIT License
Classifier: Operating System :: OS Independent
Requires-Python: >=3.6
